wdl_viewer/__init__.py
wdl_viewer/app.py
wdl_viewer/core.py
wdl_viewer/server.py
wdl_viewer/wdl/__init__.py
wdl_viewer/wdl/utils.py
wdl_viewer/wdl/wdl_graph.py
wdl_viewer/wdl/versions/__init__.py
wdl_viewer/wdl/versions/development.py
wdl_viewer/wdl/versions/v1_0.py
wdl_viewer/wdl/versions/v1_1.py
wdl_viewer-0.0.1.dist-info/METADATA
wdl_viewer-0.0.1.dist-info/WHEEL
wdl_viewer-0.0.1.dist-info/top_level.txt
wdl_viewer-0.0.1.dist-info/RECORD
